whitenoise/__init__.py
whitenoise/base.py
whitenoise/compress.py
whitenoise/media_types.py
whitenoise/middleware.py
whitenoise/responders.py
whitenoise/storage.py
whitenoise/string_utils.py
whitenoise/runserver_nostatic/__init__.py
whitenoise/runserver_nostatic/management/__init__.py
whitenoise/runserver_nostatic/management/commands/__init__.py
whitenoise/runserver_nostatic/management/commands/runserver.py
whitenoise-6.8.2.dist-info/LICENSE
whitenoise-6.8.2.dist-info/METADATA
whitenoise-6.8.2.dist-info/WHEEL
whitenoise-6.8.2.dist-info/top_level.txt
whitenoise-6.8.2.dist-info/RECORD
