Metadata-Version: 2.1
Name: whitenoise
Version: 6.8.2
Summary: Radically simplified static file serving for WSGI applications
Author: David Evans
Maintainer: David Evans
Maintainer-email: Adam Johnson <me@adamj.eu>
Project-URL: Changelog, https://whitenoise.readthedocs.io/en/stable/changelog.html
Project-URL: Documentation, https://whitenoise.readthedocs.io/
Project-URL: Repository, https://github.com/evansd/whitenoise
Keywords: Django
Classifier: Development Status :: 5 - Production/Stable
Classifier: Framework :: Django
Classifier: Framework :: Django :: 4.2
Classifier: Framework :: Django :: 5.0
Classifier: Framework :: Django :: 5.1
Classifier: Intended Audience :: Developers
Classifier: License :: OSI Approved :: MIT License
Classifier: Operating System :: OS Independent
Classifier: Programming Language :: Python :: 3 :: Only
Classifier: Programming Language :: Python :: 3.9
Classifier: Programming Language :: Python :: 3.10
Classifier: Programming Language :: Python :: 3.11
Classifier: Programming Language :: Python :: 3.12
Classifier: Programming Language :: Python :: 3.13
Classifier: Programming Language :: Python :: Implementation :: CPython
Classifier: Topic :: Internet :: WWW/HTTP :: WSGI :: Middleware
Classifier: Typing :: Typed
Requires-Python: >=3.9
License-File: LICENSE
Provides-Extra: brotli
Requires-Dist: brotli; extra == "brotli"
